wheel_of_fortune/__init__.py
wheel_of_fortune/__main__.py
wheel_of_fortune/decorators.py
wheel_of_fortune/file_handler.py
wheel_of_fortune/game.py
wheel_of_fortune/utils.py
wheeloffortune-0.1.0.dist-info/METADATA
wheeloffortune-0.1.0.dist-info/WHEEL
wheeloffortune-0.1.0.dist-info/top_level.txt
wheeloffortune-0.1.0.dist-info/RECORD
