Metadata-Version: 2.4
Name: WheelOfFortune
Version: 0.1.0
Summary: Игра "Поле чудес" на Python
Home-page: https://github.com/kekeIRL/wheel-of-fortune-game
Author: Страхов Арсений Павлович
Author-email: arsenijstrahov9@gmail.com
Classifier: Programming Language :: Python :: 3
Classifier: License :: OSI Approved :: MIT License
Classifier: Operating System :: OS Independent
Requires-Python: >=3.6
Dynamic: author
Dynamic: author-email
Dynamic: classifier
Dynamic: description
Dynamic: description-content-type
Dynamic: home-page
Dynamic: requires-python
Dynamic: summary
